[
  {
    "path": "posts/article 4/",
    "title": "Article 4: Bioluminescent tag to detect DNA break repair",
    "description": "Check out how scientist use bioluminescence to fight cancer!",
    "author": [
      {
        "name": "De Tandt Bastien",
        "url": {}
      }
    ],
    "date": "2020-12-04",
    "categories": [
      "English for Science"
    ],
    "preview": {},
    "last_modified": "2020-12-04T11:40:54+01:00"
  },
  {
    "path": "posts/meal/",
    "title": "My English Activity Log : MEAL",
    "description": {},
    "author": [
      {
        "name": "De Tandt Bastien",
        "url": {}
      }
    ],
    "date": "2020-12-04",
    "categories": [
      "English for Science",
      "M.E.A.L."
    ],
    "preview": {},
    "last_modified": "2020-12-04T11:53:42+01:00"
  },
  {
    "path": "posts/Graph SDD module4/",
    "title": "Graph for data science module 4",
    "description": "The selected dataset is urchin_bio. It is a dataset of sea urchins biometry that shows several features from *Paracentrotus lividus* who have been sinned in Brittany or in urchins farm in Normandy.",
    "author": [
      {
        "name": "De Tandt Bastien",
        "url": {}
      }
    ],
    "date": "2020-11-10",
    "categories": [
      "Data Sciences I"
    ],
    "preview": "posts/Graph SDD module4/graph-SDD_files/figure-html5/unnamed-chunk-3-1.png",
    "last_modified": "2020-11-13T09:00:01+01:00",
    "preview_width": 1248,
    "preview_height": 768
  },
  {
    "path": "posts/Article 3/",
    "title": "Article 3: Newly discovered gene may give ‘sea pickles’ their glow.",
    "description": "In this third article, scientists have found how pyrosomes produce their light!",
    "author": [
      {
        "name": "De Tandt Bastien",
        "url": {}
      }
    ],
    "date": "2020-11-07",
    "categories": [
      "English for Science"
    ],
    "preview": {},
    "last_modified": "2020-12-04T11:34:43+01:00"
  },
  {
    "path": "posts/Article 2/",
    "title": "Article 2 : Fireflies shed light on the function of mitochondria",
    "description": "In this second article, we see how bioluminescence is used to monitor the activity of mitochondria.",
    "author": [
      {
        "name": "De Tandt Bastien",
        "url": {}
      }
    ],
    "date": "2020-11-03",
    "categories": [
      "English for Science"
    ],
    "preview": {},
    "last_modified": "2020-12-04T11:28:55+01:00"
  },
  {
    "path": "posts/Article1/",
    "title": "Article 1 : Flashes bright when squeezed tight: How single-celled organisms light up the oceans",
    "description": "In this first article, we begin our journey into my topic, bioluminescence ! We take a closer look to an organism who can produce light and make the oceans shine.",
    "author": [
      {
        "name": "De Tandt Bastien",
        "url": {}
      }
    ],
    "date": "2020-10-22",
    "categories": [
      "English for Science"
    ],
    "preview": {},
    "last_modified": "2020-12-04T11:34:32+01:00"
  },
  {
    "path": "posts/2019-10-24-bacteria-antobiotics/",
    "title": "Bacterium adaptation",
    "description": "Analysis of \"More than 6,000 antibiotic resistance genes discovered in the bacteria that inhabit the human gut\"",
    "author": [
      {
        "name": "Student Unknown",
        "url": {}
      },
      {
        "name": "Nicolas Devilez",
        "url": {}
      },
      {
        "name": "Engels Guyliann",
        "url": "https://guyliann.netlify.com/fr"
      }
    ],
    "date": "2020-10-21",
    "categories": [
      "English for Science",
      "Bacteria",
      "Adaptation"
    ],
    "preview": "posts/2019-10-24-bacteria-antobiotics/images/jpg120051fa.png",
    "last_modified": "2020-11-09T18:09:55+01:00",
    "preview_width": 3333,
    "preview_height": 2667
  },
  {
    "path": "posts/about/",
    "title": "About Me",
    "description": {},
    "author": [
      {
        "name": "De Tandt Bastien",
        "url": {}
      }
    ],
    "date": "2020-10-21",
    "categories": [],
    "preview": {},
    "last_modified": "2020-11-09T18:09:55+01:00"
  }
]
